rwdq/__init__.py
rwdq/main.py
rwdq-0.1.3.dist-info/LICENSE
rwdq-0.1.3.dist-info/METADATA
rwdq-0.1.3.dist-info/WHEEL
rwdq-0.1.3.dist-info/entry_points.txt
rwdq-0.1.3.dist-info/top_level.txt
rwdq-0.1.3.dist-info/RECORD
