Metadata-Version: 2.1
Name: rwdq
Version: 0.1.3
Summary: A tool for querying real-world graph database
Home-page: https://github.com/zxj0302/rwdq
Author: Zhu Xiangju
Author-email: zhuxiangjv@gmail.com
Classifier: Programming Language :: Python :: 3
Classifier: License :: OSI Approved :: MIT License
Classifier: Operating System :: OS Independent
Requires-Python: >=3.9
License-File: LICENSE
Requires-Dist: torch
Requires-Dist: torch-geometric
